{"BaseModel.8ad75c96-6c16-4b87-9ab4-84d33df588b7": {"updated_at": "2019-06-30T19:08:47.253552", "__class__": "BaseModel", "id": "8ad75c96-6c16-4b87-9ab4-84d33df588b7", "created_at": "2019-06-30T19:08:47.253525", "name": "Holberton", "my_number": 89}, "BaseModel.ad999e82-ce14-4f0c-96f1-5b5403fc26e4": {"updated_at": "2019-06-30T19:08:53.631941", "__class__": "BaseModel", "id": "ad999e82-ce14-4f0c-96f1-5b5403fc26e4", "created_at": "2019-06-30T19:08:53.631905", "name": "Holberton", "my_number": 89}, "BaseModel.535adcf2-646b-44e3-be68-f9ec227f41e2": {"updated_at": "2019-06-30T19:08:55.242214", "__class__": "BaseModel", "id": "535adcf2-646b-44e3-be68-f9ec227f41e2", "created_at": "2019-06-30T19:08:55.242175", "name": "Holberton", "my_number": 89}, "BaseModel.0978f2de-e798-4d40-a992-570be9090eb4": {"updated_at": "2019-06-30T19:08:56.255015", "__class__": "BaseModel", "id": "0978f2de-e798-4d40-a992-570be9090eb4", "created_at": "2019-06-30T19:08:56.254982", "name": "Holberton", "my_number": 89}, "BaseModel.ee4994a8-b267-4134-8f74-4b57cc491a3d": {"updated_at": "2019-06-30T19:08:57.774874", "__class__": "BaseModel", "id": "ee4994a8-b267-4134-8f74-4b57cc491a3d", "created_at": "2019-06-30T19:08:57.774844", "name": "Holberton", "my_number": 89}, "BaseModel.171bf63b-966e-4391-b995-dd519ee60ff7": {"updated_at": "2019-06-30T19:08:54.070984", "__class__": "BaseModel", "id": "171bf63b-966e-4391-b995-dd519ee60ff7", "created_at": "2019-06-30T19:08:54.070953", "name": "Holberton", "my_number": 89}, "BaseModel.4db6dbe1-a63a-402b-af5f-f6074add99f5": {"updated_at": "2019-06-30T19:08:35.774167", "__class__": "BaseModel", "id": "4db6dbe1-a63a-402b-af5f-f6074add99f5", "created_at": "2019-06-30T19:08:35.774143", "name": "Holberton", "my_number": 89}, "BaseModel.aa8f580c-6031-460f-9901-84e3c7419c66": {"updated_at": "2019-06-30T19:08:51.167955", "__class__": "BaseModel", "id": "aa8f580c-6031-460f-9901-84e3c7419c66", "created_at": "2019-06-30T19:08:51.167925", "name": "Holberton", "my_number": 89}, "BaseModel.2f05f9bc-df2b-45f5-8ac1-897fbe360c12": {"updated_at": "2019-06-30T19:08:53.171301", "__class__": "BaseModel", "id": "2f05f9bc-df2b-45f5-8ac1-897fbe360c12", "created_at": "2019-06-30T19:08:53.171271", "name": "Holberton", "my_number": 89}, "BaseModel.b37c1409-859b-4b59-8ad9-dea61fd59b5e": {"updated_at": "2019-06-30T19:08:52.542023", "__class__": "BaseModel", "id": "b37c1409-859b-4b59-8ad9-dea61fd59b5e", "created_at": "2019-06-30T19:08:52.541993", "name": "Holberton", "my_number": 89}, "BaseModel.de521934-5dba-4e7b-96fa-d697955c1201": {"updated_at": "2019-06-30T19:08:56.952864", "__class__": "BaseModel", "id": "de521934-5dba-4e7b-96fa-d697955c1201", "created_at": "2019-06-30T19:08:56.952832", "name": "Holberton", "my_number": 89}, "BaseModel.d87b02db-463c-4fcc-8dcb-ac1de4d6751f": {"updated_at": "2019-06-30T19:08:40.017721", "__class__": "BaseModel", "id": "d87b02db-463c-4fcc-8dcb-ac1de4d6751f", "created_at": "2019-06-30T19:08:40.017686", "name": "Holberton", "my_number": 89}, "BaseModel.2ebc7431-af17-446c-901e-e2d7692a86e4": {"updated_at": "2019-06-30T19:08:58.347840", "__class__": "BaseModel", "id": "2ebc7431-af17-446c-901e-e2d7692a86e4", "created_at": "2019-06-30T19:08:58.347810", "name": "Holberton", "my_number": 89}}